{
  "meta": {
    "dataset": "hotpot_mini.json",
    "mode": "real",
    "num_records": 232,
    "agents": [
      "react",
      "reflexion"
    ]
  },
  "summary": {
    "react": {
      "count": 116,
      "em": 0.7155,
      "avg_attempts": 1,
      "avg_token_estimate": 38.99,
      "avg_latency_ms": 3299.63
    },
    "reflexion": {
      "count": 116,
      "em": 0.9483,
      "avg_attempts": 1.3966,
      "avg_token_estimate": 88.61,
      "avg_latency_ms": 4648.92
    },
    "delta_reflexion_minus_react": {
      "em_abs": 0.2328,
      "attempts_abs": 0.3966,
      "tokens_abs": 49.62,
      "latency_abs": 1349.29
    }
  },
  "failure_modes": {
    "none": {
      "react": 83,
      "reflexion": 110
    },
    "entity_drift": {
      "react": 2,
      "reflexion": 0
    },
    "wrong_final_answer": {
      "react": 30,
      "reflexion": 6
    },
    "incomplete_multi_hop": {
      "react": 1,
      "reflexion": 0
    }
  },
  "examples": [
    {
      "qid": "hp1",
      "agent_type": "react",
      "gold_answer": "Oxford University",
      "predicted_answer": "Oxford University",
      "is_correct": true,
      "attempts": 1,
      "failure_mode": "none",
      "reflection_count": 0
    },
    {
      "qid": "hp2",
      "agent_type": "react",
      "gold_answer": "River Thames",
      "predicted_answer": "London",
      "is_correct": false,
      "attempts": 1,
      "failure_mode": "incomplete_multi_hop",
      "reflection_count": 0
    },
    {
      "qid": "hp3",
      "agent_type": "react",
      "gold_answer": "violin",
      "predicted_answer": "Violin",
      "is_correct": true,
      "attempts": 1,
      "failure_mode": "none",
      "reflection_count": 0
    },
    {
      "qid": "hp4",
      "agent_type": "react",
      "gold_answer": "Pacific Ocean",
      "predicted_answer": "Atlantic Ocean",
      "is_correct": false,
      "attempts": 1,
      "failure_mode": "wrong_final_answer",
      "reflection_count": 0
    },
    {
      "qid": "hp5",
      "agent_type": "react",
      "gold_answer": "mathematics",
      "predicted_answer": "Mathematics",
      "is_correct": true,
      "attempts": 1,
      "failure_mode": "none",
      "reflection_count": 0
    },
    {
      "qid": "hp6",
      "agent_type": "react",
      "gold_answer": "Dead Sea",
      "predicted_answer": "Red Sea",
      "is_correct": false,
      "attempts": 1,
      "failure_mode": "entity_drift",
      "reflection_count": 0
    },
    {
      "qid": "hp7",
      "agent_type": "react",
      "gold_answer": "Romance",
      "predicted_answer": "Romance language family",
      "is_correct": false,
      "attempts": 1,
      "failure_mode": "wrong_final_answer",
      "reflection_count": 0
    },
    {
      "qid": "hp8",
      "agent_type": "react",
      "gold_answer": "Himalayas",
      "predicted_answer": "Andes",
      "is_correct": false,
      "attempts": 1,
      "failure_mode": "entity_drift",
      "reflection_count": 0
    },
    {
      "qid": "hp200",
      "agent_type": "react",
      "gold_answer": "Vistula River",
      "predicted_answer": "Warsaw",
      "is_correct": false,
      "attempts": 1,
      "failure_mode": "wrong_final_answer",
      "reflection_count": 0
    },
    {
      "qid": "hp201",
      "agent_type": "react",
      "gold_answer": "Pacific Ocean",
      "predicted_answer": "Australia",
      "is_correct": false,
      "attempts": 1,
      "failure_mode": "wrong_final_answer",
      "reflection_count": 0
    },
    {
      "qid": "hp202",
      "agent_type": "react",
      "gold_answer": "Mediterranean Sea",
      "predicted_answer": "Italy",
      "is_correct": false,
      "attempts": 1,
      "failure_mode": "wrong_final_answer",
      "reflection_count": 0
    },
    {
      "qid": "hp203",
      "agent_type": "react",
      "gold_answer": "Alps",
      "predicted_answer": "Germany",
      "is_correct": false,
      "attempts": 1,
      "failure_mode": "wrong_final_answer",
      "reflection_count": 0
    },
    {
      "qid": "hp204",
      "agent_type": "react",
      "gold_answer": "Romance",
      "predicted_answer": "piano",
      "is_correct": false,
      "attempts": 1,
      "failure_mode": "wrong_final_answer",
      "reflection_count": 0
    },
    {
      "qid": "hp205",
      "agent_type": "react",
      "gold_answer": "Sea of Marmara",
      "predicted_answer": "Portuguese",
      "is_correct": false,
      "attempts": 1,
      "failure_mode": "wrong_final_answer",
      "reflection_count": 0
    },
    {
      "qid": "hp206",
      "agent_type": "react",
      "gold_answer": "Atlantic Ocean",
      "predicted_answer": "Pacific Ocean",
      "is_correct": false,
      "attempts": 1,
      "failure_mode": "wrong_final_answer",
      "reflection_count": 0
    },
    {
      "qid": "hp207",
      "agent_type": "react",
      "gold_answer": "Pacific Ocean",
      "predicted_answer": "Atlantic Ocean",
      "is_correct": false,
      "attempts": 1,
      "failure_mode": "wrong_final_answer",
      "reflection_count": 0
    },
    {
      "qid": "hp100",
      "agent_type": "react",
      "gold_answer": "Oxford University",
      "predicted_answer": "Oxford",
      "is_correct": true,
      "attempts": 1,
      "failure_mode": "none",
      "reflection_count": 0
    },
    {
      "qid": "hp101",
      "agent_type": "react",
      "gold_answer": "River Thames",
      "predicted_answer": "Thames",
      "is_correct": false,
      "attempts": 1,
      "failure_mode": "wrong_final_answer",
      "reflection_count": 0
    },
    {
      "qid": "hp102",
      "agent_type": "react",
      "gold_answer": "Pacific Ocean",
      "predicted_answer": "Pacific Ocean",
      "is_correct": true,
      "attempts": 1,
      "failure_mode": "none",
      "reflection_count": 0
    },
    {
      "qid": "hp103",
      "agent_type": "react",
      "gold_answer": "Paris",
      "predicted_answer": "Paris",
      "is_correct": true,
      "attempts": 1,
      "failure_mode": "none",
      "reflection_count": 0
    },
    {
      "qid": "hp104",
      "agent_type": "react",
      "gold_answer": "violin",
      "predicted_answer": "violin",
      "is_correct": true,
      "attempts": 1,
      "failure_mode": "none",
      "reflection_count": 0
    },
    {
      "qid": "hp105",
      "agent_type": "react",
      "gold_answer": "Oxford University",
      "predicted_answer": "Oxford University",
      "is_correct": true,
      "attempts": 1,
      "failure_mode": "none",
      "reflection_count": 0
    },
    {
      "qid": "hp106",
      "agent_type": "react",
      "gold_answer": "River Thames",
      "predicted_answer": "Thames",
      "is_correct": false,
      "attempts": 1,
      "failure_mode": "wrong_final_answer",
      "reflection_count": 0
    },
    {
      "qid": "hp107",
      "agent_type": "react",
      "gold_answer": "Pacific Ocean",
      "predicted_answer": "Pacific Ocean",
      "is_correct": true,
      "attempts": 1,
      "failure_mode": "none",
      "reflection_count": 0
    },
    {
      "qid": "hp108",
      "agent_type": "react",
      "gold_answer": "Paris",
      "predicted_answer": "Paris",
      "is_correct": true,
      "attempts": 1,
      "failure_mode": "none",
      "reflection_count": 0
    },
    {
      "qid": "hp109",
      "agent_type": "react",
      "gold_answer": "violin",
      "predicted_answer": "violin",
      "is_correct": true,
      "attempts": 1,
      "failure_mode": "none",
      "reflection_count": 0
    },
    {
      "qid": "hp110",
      "agent_type": "react",
      "gold_answer": "Oxford University",
      "predicted_answer": "Oxford",
      "is_correct": true,
      "attempts": 1,
      "failure_mode": "none",
      "reflection_count": 0
    },
    {
      "qid": "hp111",
      "agent_type": "react",
      "gold_answer": "River Thames",
      "predicted_answer": "Thames",
      "is_correct": false,
      "attempts": 1,
      "failure_mode": "wrong_final_answer",
      "reflection_count": 0
    },
    {
      "qid": "hp112",
      "agent_type": "react",
      "gold_answer": "Pacific Ocean",
      "predicted_answer": "Pacific Ocean",
      "is_correct": true,
      "attempts": 1,
      "failure_mode": "none",
      "reflection_count": 0
    },
    {
      "qid": "hp113",
      "agent_type": "react",
      "gold_answer": "Paris",
      "predicted_answer": "Paris",
      "is_correct": true,
      "attempts": 1,
      "failure_mode": "none",
      "reflection_count": 0
    },
    {
      "qid": "hp114",
      "agent_type": "react",
      "gold_answer": "violin",
      "predicted_answer": "violin",
      "is_correct": true,
      "attempts": 1,
      "failure_mode": "none",
      "reflection_count": 0
    },
    {
      "qid": "hp115",
      "agent_type": "react",
      "gold_answer": "Oxford University",
      "predicted_answer": "Oxford",
      "is_correct": true,
      "attempts": 1,
      "failure_mode": "none",
      "reflection_count": 0
    },
    {
      "qid": "hp116",
      "agent_type": "react",
      "gold_answer": "River Thames",
      "predicted_answer": "Thames",
      "is_correct": false,
      "attempts": 1,
      "failure_mode": "wrong_final_answer",
      "reflection_count": 0
    },
    {
      "qid": "hp117",
      "agent_type": "react",
      "gold_answer": "Pacific Ocean",
      "predicted_answer": "Pacific Ocean",
      "is_correct": true,
      "attempts": 1,
      "failure_mode": "none",
      "reflection_count": 0
    },
    {
      "qid": "hp118",
      "agent_type": "react",
      "gold_answer": "Paris",
      "predicted_answer": "Paris",
      "is_correct": true,
      "attempts": 1,
      "failure_mode": "none",
      "reflection_count": 0
    },
    {
      "qid": "hp119",
      "agent_type": "react",
      "gold_answer": "violin",
      "predicted_answer": "violin",
      "is_correct": true,
      "attempts": 1,
      "failure_mode": "none",
      "reflection_count": 0
    },
    {
      "qid": "hp120",
      "agent_type": "react",
      "gold_answer": "Oxford University",
      "predicted_answer": "Oxford University",
      "is_correct": true,
      "attempts": 1,
      "failure_mode": "none",
      "reflection_count": 0
    },
    {
      "qid": "hp121",
      "agent_type": "react",
      "gold_answer": "River Thames",
      "predicted_answer": "Thames",
      "is_correct": false,
      "attempts": 1,
      "failure_mode": "wrong_final_answer",
      "reflection_count": 0
    },
    {
      "qid": "hp122",
      "agent_type": "react",
      "gold_answer": "Pacific Ocean",
      "predicted_answer": "Pacific Ocean",
      "is_correct": true,
      "attempts": 1,
      "failure_mode": "none",
      "reflection_count": 0
    },
    {
      "qid": "hp123",
      "agent_type": "react",
      "gold_answer": "Paris",
      "predicted_answer": "Paris",
      "is_correct": true,
      "attempts": 1,
      "failure_mode": "none",
      "reflection_count": 0
    },
    {
      "qid": "hp124",
      "agent_type": "react",
      "gold_answer": "violin",
      "predicted_answer": "Violin",
      "is_correct": true,
      "attempts": 1,
      "failure_mode": "none",
      "reflection_count": 0
    },
    {
      "qid": "hp125",
      "agent_type": "react",
      "gold_answer": "Oxford University",
      "predicted_answer": "Oxford",
      "is_correct": true,
      "attempts": 1,
      "failure_mode": "none",
      "reflection_count": 0
    },
    {
      "qid": "hp126",
      "agent_type": "react",
      "gold_answer": "River Thames",
      "predicted_answer": "Thames",
      "is_correct": false,
      "attempts": 1,
      "failure_mode": "wrong_final_answer",
      "reflection_count": 0
    },
    {
      "qid": "hp127",
      "agent_type": "react",
      "gold_answer": "Pacific Ocean",
      "predicted_answer": "Pacific Ocean",
      "is_correct": true,
      "attempts": 1,
      "failure_mode": "none",
      "reflection_count": 0
    },
    {
      "qid": "hp128",
      "agent_type": "react",
      "gold_answer": "Paris",
      "predicted_answer": "Paris",
      "is_correct": true,
      "attempts": 1,
      "failure_mode": "none",
      "reflection_count": 0
    },
    {
      "qid": "hp129",
      "agent_type": "react",
      "gold_answer": "violin",
      "predicted_answer": "Violin",
      "is_correct": true,
      "attempts": 1,
      "failure_mode": "none",
      "reflection_count": 0
    },
    {
      "qid": "hp130",
      "agent_type": "react",
      "gold_answer": "Oxford University",
      "predicted_answer": "Oxford",
      "is_correct": true,
      "attempts": 1,
      "failure_mode": "none",
      "reflection_count": 0
    },
    {
      "qid": "hp131",
      "agent_type": "react",
      "gold_answer": "River Thames",
      "predicted_answer": "Thames",
      "is_correct": false,
      "attempts": 1,
      "failure_mode": "wrong_final_answer",
      "reflection_count": 0
    },
    {
      "qid": "hp132",
      "agent_type": "react",
      "gold_answer": "Pacific Ocean",
      "predicted_answer": "Pacific Ocean",
      "is_correct": true,
      "attempts": 1,
      "failure_mode": "none",
      "reflection_count": 0
    },
    {
      "qid": "hp133",
      "agent_type": "react",
      "gold_answer": "Paris",
      "predicted_answer": "Paris",
      "is_correct": true,
      "attempts": 1,
      "failure_mode": "none",
      "reflection_count": 0
    },
    {
      "qid": "hp134",
      "agent_type": "react",
      "gold_answer": "violin",
      "predicted_answer": "violin",
      "is_correct": true,
      "attempts": 1,
      "failure_mode": "none",
      "reflection_count": 0
    },
    {
      "qid": "hp135",
      "agent_type": "react",
      "gold_answer": "Oxford University",
      "predicted_answer": "Oxford University",
      "is_correct": true,
      "attempts": 1,
      "failure_mode": "none",
      "reflection_count": 0
    },
    {
      "qid": "hp136",
      "agent_type": "react",
      "gold_answer": "River Thames",
      "predicted_answer": "Thames",
      "is_correct": false,
      "attempts": 1,
      "failure_mode": "wrong_final_answer",
      "reflection_count": 0
    },
    {
      "qid": "hp137",
      "agent_type": "react",
      "gold_answer": "Pacific Ocean",
      "predicted_answer": "Pacific Ocean",
      "is_correct": true,
      "attempts": 1,
      "failure_mode": "none",
      "reflection_count": 0
    },
    {
      "qid": "hp138",
      "agent_type": "react",
      "gold_answer": "Paris",
      "predicted_answer": "Paris",
      "is_correct": true,
      "attempts": 1,
      "failure_mode": "none",
      "reflection_count": 0
    },
    {
      "qid": "hp139",
      "agent_type": "react",
      "gold_answer": "violin",
      "predicted_answer": "violin",
      "is_correct": true,
      "attempts": 1,
      "failure_mode": "none",
      "reflection_count": 0
    },
    {
      "qid": "hp140",
      "agent_type": "react",
      "gold_answer": "Oxford University",
      "predicted_answer": "Oxford University",
      "is_correct": true,
      "attempts": 1,
      "failure_mode": "none",
      "reflection_count": 0
    },
    {
      "qid": "hp141",
      "agent_type": "react",
      "gold_answer": "River Thames",
      "predicted_answer": "Thames",
      "is_correct": false,
      "attempts": 1,
      "failure_mode": "wrong_final_answer",
      "reflection_count": 0
    },
    {
      "qid": "hp142",
      "agent_type": "react",
      "gold_answer": "Pacific Ocean",
      "predicted_answer": "Pacific Ocean",
      "is_correct": true,
      "attempts": 1,
      "failure_mode": "none",
      "reflection_count": 0
    },
    {
      "qid": "hp143",
      "agent_type": "react",
      "gold_answer": "Paris",
      "predicted_answer": "Paris",
      "is_correct": true,
      "attempts": 1,
      "failure_mode": "none",
      "reflection_count": 0
    },
    {
      "qid": "hp144",
      "agent_type": "react",
      "gold_answer": "violin",
      "predicted_answer": "Violin",
      "is_correct": true,
      "attempts": 1,
      "failure_mode": "none",
      "reflection_count": 0
    },
    {
      "qid": "hp145",
      "agent_type": "react",
      "gold_answer": "Oxford University",
      "predicted_answer": "Oxford University",
      "is_correct": true,
      "attempts": 1,
      "failure_mode": "none",
      "reflection_count": 0
    },
    {
      "qid": "hp146",
      "agent_type": "react",
      "gold_answer": "River Thames",
      "predicted_answer": "Thames",
      "is_correct": false,
      "attempts": 1,
      "failure_mode": "wrong_final_answer",
      "reflection_count": 0
    },
    {
      "qid": "hp147",
      "agent_type": "react",
      "gold_answer": "Pacific Ocean",
      "predicted_answer": "Pacific Ocean",
      "is_correct": true,
      "attempts": 1,
      "failure_mode": "none",
      "reflection_count": 0
    },
    {
      "qid": "hp148",
      "agent_type": "react",
      "gold_answer": "Paris",
      "predicted_answer": "Paris",
      "is_correct": true,
      "attempts": 1,
      "failure_mode": "none",
      "reflection_count": 0
    },
    {
      "qid": "hp149",
      "agent_type": "react",
      "gold_answer": "violin",
      "predicted_answer": "violin",
      "is_correct": true,
      "attempts": 1,
      "failure_mode": "none",
      "reflection_count": 0
    },
    {
      "qid": "hp150",
      "agent_type": "react",
      "gold_answer": "Oxford University",
      "predicted_answer": "Oxford University",
      "is_correct": true,
      "attempts": 1,
      "failure_mode": "none",
      "reflection_count": 0
    },
    {
      "qid": "hp151",
      "agent_type": "react",
      "gold_answer": "River Thames",
      "predicted_answer": "Thames",
      "is_correct": false,
      "attempts": 1,
      "failure_mode": "wrong_final_answer",
      "reflection_count": 0
    },
    {
      "qid": "hp152",
      "agent_type": "react",
      "gold_answer": "Pacific Ocean",
      "predicted_answer": "Pacific Ocean",
      "is_correct": true,
      "attempts": 1,
      "failure_mode": "none",
      "reflection_count": 0
    },
    {
      "qid": "hp153",
      "agent_type": "react",
      "gold_answer": "Paris",
      "predicted_answer": "Paris",
      "is_correct": true,
      "attempts": 1,
      "failure_mode": "none",
      "reflection_count": 0
    },
    {
      "qid": "hp154",
      "agent_type": "react",
      "gold_answer": "violin",
      "predicted_answer": "violin",
      "is_correct": true,
      "attempts": 1,
      "failure_mode": "none",
      "reflection_count": 0
    },
    {
      "qid": "hp155",
      "agent_type": "react",
      "gold_answer": "Oxford University",
      "predicted_answer": "Oxford University",
      "is_correct": true,
      "attempts": 1,
      "failure_mode": "none",
      "reflection_count": 0
    },
    {
      "qid": "hp156",
      "agent_type": "react",
      "gold_answer": "River Thames",
      "predicted_answer": "Thames",
      "is_correct": false,
      "attempts": 1,
      "failure_mode": "wrong_final_answer",
      "reflection_count": 0
    },
    {
      "qid": "hp157",
      "agent_type": "react",
      "gold_answer": "Pacific Ocean",
      "predicted_answer": "Pacific Ocean",
      "is_correct": true,
      "attempts": 1,
      "failure_mode": "none",
      "reflection_count": 0
    },
    {
      "qid": "hp158",
      "agent_type": "react",
      "gold_answer": "Paris",
      "predicted_answer": "Paris",
      "is_correct": true,
      "attempts": 1,
      "failure_mode": "none",
      "reflection_count": 0
    },
    {
      "qid": "hp159",
      "agent_type": "react",
      "gold_answer": "violin",
      "predicted_answer": "violin",
      "is_correct": true,
      "attempts": 1,
      "failure_mode": "none",
      "reflection_count": 0
    },
    {
      "qid": "hp160",
      "agent_type": "react",
      "gold_answer": "Oxford University",
      "predicted_answer": "Oxford University",
      "is_correct": true,
      "attempts": 1,
      "failure_mode": "none",
      "reflection_count": 0
    },
    {
      "qid": "hp161",
      "agent_type": "react",
      "gold_answer": "River Thames",
      "predicted_answer": "Thames",
      "is_correct": false,
      "attempts": 1,
      "failure_mode": "wrong_final_answer",
      "reflection_count": 0
    },
    {
      "qid": "hp162",
      "agent_type": "react",
      "gold_answer": "Pacific Ocean",
      "predicted_answer": "Pacific Ocean",
      "is_correct": true,
      "attempts": 1,
      "failure_mode": "none",
      "reflection_count": 0
    },
    {
      "qid": "hp163",
      "agent_type": "react",
      "gold_answer": "Paris",
      "predicted_answer": "Paris",
      "is_correct": true,
      "attempts": 1,
      "failure_mode": "none",
      "reflection_count": 0
    },
    {
      "qid": "hp164",
      "agent_type": "react",
      "gold_answer": "violin",
      "predicted_answer": "violin",
      "is_correct": true,
      "attempts": 1,
      "failure_mode": "none",
      "reflection_count": 0
    },
    {
      "qid": "hp165",
      "agent_type": "react",
      "gold_answer": "Oxford University",
      "predicted_answer": "Oxford University",
      "is_correct": true,
      "attempts": 1,
      "failure_mode": "none",
      "reflection_count": 0
    },
    {
      "qid": "hp166",
      "agent_type": "react",
      "gold_answer": "River Thames",
      "predicted_answer": "Thames",
      "is_correct": false,
      "attempts": 1,
      "failure_mode": "wrong_final_answer",
      "reflection_count": 0
    },
    {
      "qid": "hp167",
      "agent_type": "react",
      "gold_answer": "Pacific Ocean",
      "predicted_answer": "Pacific Ocean",
      "is_correct": true,
      "attempts": 1,
      "failure_mode": "none",
      "reflection_count": 0
    },
    {
      "qid": "hp168",
      "agent_type": "react",
      "gold_answer": "Paris",
      "predicted_answer": "Paris",
      "is_correct": true,
      "attempts": 1,
      "failure_mode": "none",
      "reflection_count": 0
    },
    {
      "qid": "hp169",
      "agent_type": "react",
      "gold_answer": "violin",
      "predicted_answer": "violin",
      "is_correct": true,
      "attempts": 1,
      "failure_mode": "none",
      "reflection_count": 0
    },
    {
      "qid": "hp170",
      "agent_type": "react",
      "gold_answer": "Oxford University",
      "predicted_answer": "Oxford University",
      "is_correct": true,
      "attempts": 1,
      "failure_mode": "none",
      "reflection_count": 0
    },
    {
      "qid": "hp171",
      "agent_type": "react",
      "gold_answer": "River Thames",
      "predicted_answer": "Thames",
      "is_correct": false,
      "attempts": 1,
      "failure_mode": "wrong_final_answer",
      "reflection_count": 0
    },
    {
      "qid": "hp172",
      "agent_type": "react",
      "gold_answer": "Pacific Ocean",
      "predicted_answer": "Pacific Ocean",
      "is_correct": true,
      "attempts": 1,
      "failure_mode": "none",
      "reflection_count": 0
    },
    {
      "qid": "hp173",
      "agent_type": "react",
      "gold_answer": "Paris",
      "predicted_answer": "Paris",
      "is_correct": true,
      "attempts": 1,
      "failure_mode": "none",
      "reflection_count": 0
    },
    {
      "qid": "hp174",
      "agent_type": "react",
      "gold_answer": "violin",
      "predicted_answer": "Violin",
      "is_correct": true,
      "attempts": 1,
      "failure_mode": "none",
      "reflection_count": 0
    },
    {
      "qid": "hp175",
      "agent_type": "react",
      "gold_answer": "Oxford University",
      "predicted_answer": "Oxford University",
      "is_correct": true,
      "attempts": 1,
      "failure_mode": "none",
      "reflection_count": 0
    },
    {
      "qid": "hp176",
      "agent_type": "react",
      "gold_answer": "River Thames",
      "predicted_answer": "Thames",
      "is_correct": false,
      "attempts": 1,
      "failure_mode": "wrong_final_answer",
      "reflection_count": 0
    },
    {
      "qid": "hp177",
      "agent_type": "react",
      "gold_answer": "Pacific Ocean",
      "predicted_answer": "Pacific Ocean",
      "is_correct": true,
      "attempts": 1,
      "failure_mode": "none",
      "reflection_count": 0
    },
    {
      "qid": "hp178",
      "agent_type": "react",
      "gold_answer": "Paris",
      "predicted_answer": "Paris",
      "is_correct": true,
      "attempts": 1,
      "failure_mode": "none",
      "reflection_count": 0
    },
    {
      "qid": "hp179",
      "agent_type": "react",
      "gold_answer": "violin",
      "predicted_answer": "Violin",
      "is_correct": true,
      "attempts": 1,
      "failure_mode": "none",
      "reflection_count": 0
    },
    {
      "qid": "hp180",
      "agent_type": "react",
      "gold_answer": "Oxford University",
      "predicted_answer": "Oxford University",
      "is_correct": true,
      "attempts": 1,
      "failure_mode": "none",
      "reflection_count": 0
    },
    {
      "qid": "hp181",
      "agent_type": "react",
      "gold_answer": "River Thames",
      "predicted_answer": "Thames",
      "is_correct": false,
      "attempts": 1,
      "failure_mode": "wrong_final_answer",
      "reflection_count": 0
    },
    {
      "qid": "hp182",
      "agent_type": "react",
      "gold_answer": "Pacific Ocean",
      "predicted_answer": "Pacific Ocean",
      "is_correct": true,
      "attempts": 1,
      "failure_mode": "none",
      "reflection_count": 0
    },
    {
      "qid": "hp183",
      "agent_type": "react",
      "gold_answer": "Paris",
      "predicted_answer": "Paris",
      "is_correct": true,
      "attempts": 1,
      "failure_mode": "none",
      "reflection_count": 0
    },
    {
      "qid": "hp184",
      "agent_type": "react",
      "gold_answer": "violin",
      "predicted_answer": "violin",
      "is_correct": true,
      "attempts": 1,
      "failure_mode": "none",
      "reflection_count": 0
    },
    {
      "qid": "hp185",
      "agent_type": "react",
      "gold_answer": "Oxford University",
      "predicted_answer": "Oxford University",
      "is_correct": true,
      "attempts": 1,
      "failure_mode": "none",
      "reflection_count": 0
    },
    {
      "qid": "hp186",
      "agent_type": "react",
      "gold_answer": "River Thames",
      "predicted_answer": "Thames",
      "is_correct": false,
      "attempts": 1,
      "failure_mode": "wrong_final_answer",
      "reflection_count": 0
    },
    {
      "qid": "hp187",
      "agent_type": "react",
      "gold_answer": "Pacific Ocean",
      "predicted_answer": "Pacific Ocean",
      "is_correct": true,
      "attempts": 1,
      "failure_mode": "none",
      "reflection_count": 0
    },
    {
      "qid": "hp188",
      "agent_type": "react",
      "gold_answer": "Paris",
      "predicted_answer": "Paris",
      "is_correct": true,
      "attempts": 1,
      "failure_mode": "none",
      "reflection_count": 0
    },
    {
      "qid": "hp189",
      "agent_type": "react",
      "gold_answer": "violin",
      "predicted_answer": "violin",
      "is_correct": true,
      "attempts": 1,
      "failure_mode": "none",
      "reflection_count": 0
    },
    {
      "qid": "hp190",
      "agent_type": "react",
      "gold_answer": "Oxford University",
      "predicted_answer": "Oxford University",
      "is_correct": true,
      "attempts": 1,
      "failure_mode": "none",
      "reflection_count": 0
    },
    {
      "qid": "hp191",
      "agent_type": "react",
      "gold_answer": "River Thames",
      "predicted_answer": "Thames",
      "is_correct": false,
      "attempts": 1,
      "failure_mode": "wrong_final_answer",
      "reflection_count": 0
    },
    {
      "qid": "hp192",
      "agent_type": "react",
      "gold_answer": "Pacific Ocean",
      "predicted_answer": "Pacific Ocean",
      "is_correct": true,
      "attempts": 1,
      "failure_mode": "none",
      "reflection_count": 0
    },
    {
      "qid": "hp193",
      "agent_type": "react",
      "gold_answer": "Paris",
      "predicted_answer": "Paris",
      "is_correct": true,
      "attempts": 1,
      "failure_mode": "none",
      "reflection_count": 0
    },
    {
      "qid": "hp194",
      "agent_type": "react",
      "gold_answer": "violin",
      "predicted_answer": "violin",
      "is_correct": true,
      "attempts": 1,
      "failure_mode": "none",
      "reflection_count": 0
    },
    {
      "qid": "hp195",
      "agent_type": "react",
      "gold_answer": "Oxford University",
      "predicted_answer": "Oxford University",
      "is_correct": true,
      "attempts": 1,
      "failure_mode": "none",
      "reflection_count": 0
    },
    {
      "qid": "hp196",
      "agent_type": "react",
      "gold_answer": "River Thames",
      "predicted_answer": "Thames",
      "is_correct": false,
      "attempts": 1,
      "failure_mode": "wrong_final_answer",
      "reflection_count": 0
    },
    {
      "qid": "hp197",
      "agent_type": "react",
      "gold_answer": "Pacific Ocean",
      "predicted_answer": "Pacific Ocean",
      "is_correct": true,
      "attempts": 1,
      "failure_mode": "none",
      "reflection_count": 0
    },
    {
      "qid": "hp198",
      "agent_type": "react",
      "gold_answer": "Paris",
      "predicted_answer": "Paris",
      "is_correct": true,
      "attempts": 1,
      "failure_mode": "none",
      "reflection_count": 0
    },
    {
      "qid": "hp199",
      "agent_type": "react",
      "gold_answer": "violin",
      "predicted_answer": "violin",
      "is_correct": true,
      "attempts": 1,
      "failure_mode": "none",
      "reflection_count": 0
    },
    {
      "qid": "hp1",
      "agent_type": "reflexion",
      "gold_answer": "Oxford University",
      "predicted_answer": "Oxford University",
      "is_correct": true,
      "attempts": 1,
      "failure_mode": "none",
      "reflection_count": 0
    },
    {
      "qid": "hp2",
      "agent_type": "reflexion",
      "gold_answer": "River Thames",
      "predicted_answer": "River Thames",
      "is_correct": true,
      "attempts": 2,
      "failure_mode": "none",
      "reflection_count": 1
    },
    {
      "qid": "hp3",
      "agent_type": "reflexion",
      "gold_answer": "violin",
      "predicted_answer": "Violin",
      "is_correct": true,
      "attempts": 1,
      "failure_mode": "none",
      "reflection_count": 0
    },
    {
      "qid": "hp4",
      "agent_type": "reflexion",
      "gold_answer": "Pacific Ocean",
      "predicted_answer": "Pacific Ocean",
      "is_correct": true,
      "attempts": 2,
      "failure_mode": "none",
      "reflection_count": 1
    },
    {
      "qid": "hp5",
      "agent_type": "reflexion",
      "gold_answer": "mathematics",
      "predicted_answer": "Mathematics",
      "is_correct": true,
      "attempts": 1,
      "failure_mode": "none",
      "reflection_count": 0
    },
    {
      "qid": "hp6",
      "agent_type": "reflexion",
      "gold_answer": "Dead Sea",
      "predicted_answer": "Dead Sea",
      "is_correct": true,
      "attempts": 2,
      "failure_mode": "none",
      "reflection_count": 1
    },
    {
      "qid": "hp7",
      "agent_type": "reflexion",
      "gold_answer": "Romance",
      "predicted_answer": "Romance",
      "is_correct": true,
      "attempts": 2,
      "failure_mode": "none",
      "reflection_count": 1
    },
    {
      "qid": "hp8",
      "agent_type": "reflexion",
      "gold_answer": "Himalayas",
      "predicted_answer": "Himalayas",
      "is_correct": true,
      "attempts": 2,
      "failure_mode": "none",
      "reflection_count": 1
    },
    {
      "qid": "hp200",
      "agent_type": "reflexion",
      "gold_answer": "Vistula River",
      "predicted_answer": "Vistula River",
      "is_correct": true,
      "attempts": 2,
      "failure_mode": "none",
      "reflection_count": 1
    },
    {
      "qid": "hp201",
      "agent_type": "reflexion",
      "gold_answer": "Pacific Ocean",
      "predicted_answer": "Pacific Ocean",
      "is_correct": true,
      "attempts": 2,
      "failure_mode": "none",
      "reflection_count": 1
    },
    {
      "qid": "hp202",
      "agent_type": "reflexion",
      "gold_answer": "Mediterranean Sea",
      "predicted_answer": "Mediterranean Sea",
      "is_correct": true,
      "attempts": 2,
      "failure_mode": "none",
      "reflection_count": 1
    },
    {
      "qid": "hp203",
      "agent_type": "reflexion",
      "gold_answer": "Alps",
      "predicted_answer": "The Alps",
      "is_correct": true,
      "attempts": 2,
      "failure_mode": "none",
      "reflection_count": 1
    },
    {
      "qid": "hp204",
      "agent_type": "reflexion",
      "gold_answer": "Romance",
      "predicted_answer": "Romance",
      "is_correct": true,
      "attempts": 2,
      "failure_mode": "none",
      "reflection_count": 1
    },
    {
      "qid": "hp205",
      "agent_type": "reflexion",
      "gold_answer": "Sea of Marmara",
      "predicted_answer": "The Sea of Marmara.",
      "is_correct": true,
      "attempts": 3,
      "failure_mode": "none",
      "reflection_count": 2
    },
    {
      "qid": "hp206",
      "agent_type": "reflexion",
      "gold_answer": "Atlantic Ocean",
      "predicted_answer": "Atlantic Ocean",
      "is_correct": true,
      "attempts": 2,
      "failure_mode": "none",
      "reflection_count": 1
    },
    {
      "qid": "hp207",
      "agent_type": "reflexion",
      "gold_answer": "Pacific Ocean",
      "predicted_answer": "Pacific Ocean",
      "is_correct": true,
      "attempts": 2,
      "failure_mode": "none",
      "reflection_count": 1
    },
    {
      "qid": "hp100",
      "agent_type": "reflexion",
      "gold_answer": "Oxford University",
      "predicted_answer": "Oxford University",
      "is_correct": true,
      "attempts": 1,
      "failure_mode": "none",
      "reflection_count": 0
    },
    {
      "qid": "hp101",
      "agent_type": "reflexion",
      "gold_answer": "River Thames",
      "predicted_answer": "Thames",
      "is_correct": false,
      "attempts": 3,
      "failure_mode": "wrong_final_answer",
      "reflection_count": 2
    },
    {
      "qid": "hp102",
      "agent_type": "reflexion",
      "gold_answer": "Pacific Ocean",
      "predicted_answer": "Pacific Ocean",
      "is_correct": true,
      "attempts": 1,
      "failure_mode": "none",
      "reflection_count": 0
    },
    {
      "qid": "hp103",
      "agent_type": "reflexion",
      "gold_answer": "Paris",
      "predicted_answer": "Paris",
      "is_correct": true,
      "attempts": 1,
      "failure_mode": "none",
      "reflection_count": 0
    },
    {
      "qid": "hp104",
      "agent_type": "reflexion",
      "gold_answer": "violin",
      "predicted_answer": "violin",
      "is_correct": true,
      "attempts": 1,
      "failure_mode": "none",
      "reflection_count": 0
    },
    {
      "qid": "hp105",
      "agent_type": "reflexion",
      "gold_answer": "Oxford University",
      "predicted_answer": "Oxford University",
      "is_correct": true,
      "attempts": 1,
      "failure_mode": "none",
      "reflection_count": 0
    },
    {
      "qid": "hp106",
      "agent_type": "reflexion",
      "gold_answer": "River Thames",
      "predicted_answer": "Thames",
      "is_correct": false,
      "attempts": 3,
      "failure_mode": "wrong_final_answer",
      "reflection_count": 2
    },
    {
      "qid": "hp107",
      "agent_type": "reflexion",
      "gold_answer": "Pacific Ocean",
      "predicted_answer": "Pacific Ocean",
      "is_correct": true,
      "attempts": 1,
      "failure_mode": "none",
      "reflection_count": 0
    },
    {
      "qid": "hp108",
      "agent_type": "reflexion",
      "gold_answer": "Paris",
      "predicted_answer": "Paris",
      "is_correct": true,
      "attempts": 1,
      "failure_mode": "none",
      "reflection_count": 0
    },
    {
      "qid": "hp109",
      "agent_type": "reflexion",
      "gold_answer": "violin",
      "predicted_answer": "violin",
      "is_correct": true,
      "attempts": 1,
      "failure_mode": "none",
      "reflection_count": 0
    },
    {
      "qid": "hp110",
      "agent_type": "reflexion",
      "gold_answer": "Oxford University",
      "predicted_answer": "Oxford University",
      "is_correct": true,
      "attempts": 1,
      "failure_mode": "none",
      "reflection_count": 0
    },
    {
      "qid": "hp111",
      "agent_type": "reflexion",
      "gold_answer": "River Thames",
      "predicted_answer": "River Thames",
      "is_correct": true,
      "attempts": 3,
      "failure_mode": "none",
      "reflection_count": 2
    },
    {
      "qid": "hp112",
      "agent_type": "reflexion",
      "gold_answer": "Pacific Ocean",
      "predicted_answer": "Pacific Ocean",
      "is_correct": true,
      "attempts": 1,
      "failure_mode": "none",
      "reflection_count": 0
    },
    {
      "qid": "hp113",
      "agent_type": "reflexion",
      "gold_answer": "Paris",
      "predicted_answer": "Paris",
      "is_correct": true,
      "attempts": 1,
      "failure_mode": "none",
      "reflection_count": 0
    },
    {
      "qid": "hp114",
      "agent_type": "reflexion",
      "gold_answer": "violin",
      "predicted_answer": "violin",
      "is_correct": true,
      "attempts": 1,
      "failure_mode": "none",
      "reflection_count": 0
    },
    {
      "qid": "hp115",
      "agent_type": "reflexion",
      "gold_answer": "Oxford University",
      "predicted_answer": "Oxford University",
      "is_correct": true,
      "attempts": 1,
      "failure_mode": "none",
      "reflection_count": 0
    },
    {
      "qid": "hp116",
      "agent_type": "reflexion",
      "gold_answer": "River Thames",
      "predicted_answer": "River Thames",
      "is_correct": true,
      "attempts": 2,
      "failure_mode": "none",
      "reflection_count": 1
    },
    {
      "qid": "hp117",
      "agent_type": "reflexion",
      "gold_answer": "Pacific Ocean",
      "predicted_answer": "Pacific Ocean",
      "is_correct": true,
      "attempts": 1,
      "failure_mode": "none",
      "reflection_count": 0
    },
    {
      "qid": "hp118",
      "agent_type": "reflexion",
      "gold_answer": "Paris",
      "predicted_answer": "Paris",
      "is_correct": true,
      "attempts": 1,
      "failure_mode": "none",
      "reflection_count": 0
    },
    {
      "qid": "hp119",
      "agent_type": "reflexion",
      "gold_answer": "violin",
      "predicted_answer": "violin",
      "is_correct": true,
      "attempts": 1,
      "failure_mode": "none",
      "reflection_count": 0
    },
    {
      "qid": "hp120",
      "agent_type": "reflexion",
      "gold_answer": "Oxford University",
      "predicted_answer": "Oxford University",
      "is_correct": true,
      "attempts": 1,
      "failure_mode": "none",
      "reflection_count": 0
    },
    {
      "qid": "hp121",
      "agent_type": "reflexion",
      "gold_answer": "River Thames",
      "predicted_answer": "River Thames",
      "is_correct": true,
      "attempts": 2,
      "failure_mode": "none",
      "reflection_count": 1
    },
    {
      "qid": "hp122",
      "agent_type": "reflexion",
      "gold_answer": "Pacific Ocean",
      "predicted_answer": "Pacific Ocean",
      "is_correct": true,
      "attempts": 1,
      "failure_mode": "none",
      "reflection_count": 0
    },
    {
      "qid": "hp123",
      "agent_type": "reflexion",
      "gold_answer": "Paris",
      "predicted_answer": "Paris",
      "is_correct": true,
      "attempts": 1,
      "failure_mode": "none",
      "reflection_count": 0
    },
    {
      "qid": "hp124",
      "agent_type": "reflexion",
      "gold_answer": "violin",
      "predicted_answer": "violin",
      "is_correct": true,
      "attempts": 1,
      "failure_mode": "none",
      "reflection_count": 0
    },
    {
      "qid": "hp125",
      "agent_type": "reflexion",
      "gold_answer": "Oxford University",
      "predicted_answer": "Oxford University",
      "is_correct": true,
      "attempts": 1,
      "failure_mode": "none",
      "reflection_count": 0
    },
    {
      "qid": "hp126",
      "agent_type": "reflexion",
      "gold_answer": "River Thames",
      "predicted_answer": "River Thames",
      "is_correct": true,
      "attempts": 3,
      "failure_mode": "none",
      "reflection_count": 2
    },
    {
      "qid": "hp127",
      "agent_type": "reflexion",
      "gold_answer": "Pacific Ocean",
      "predicted_answer": "Pacific Ocean",
      "is_correct": true,
      "attempts": 1,
      "failure_mode": "none",
      "reflection_count": 0
    },
    {
      "qid": "hp128",
      "agent_type": "reflexion",
      "gold_answer": "Paris",
      "predicted_answer": "Paris",
      "is_correct": true,
      "attempts": 1,
      "failure_mode": "none",
      "reflection_count": 0
    },
    {
      "qid": "hp129",
      "agent_type": "reflexion",
      "gold_answer": "violin",
      "predicted_answer": "violin",
      "is_correct": true,
      "attempts": 1,
      "failure_mode": "none",
      "reflection_count": 0
    },
    {
      "qid": "hp130",
      "agent_type": "reflexion",
      "gold_answer": "Oxford University",
      "predicted_answer": "Oxford University",
      "is_correct": true,
      "attempts": 1,
      "failure_mode": "none",
      "reflection_count": 0
    },
    {
      "qid": "hp131",
      "agent_type": "reflexion",
      "gold_answer": "River Thames",
      "predicted_answer": "River Thames",
      "is_correct": true,
      "attempts": 2,
      "failure_mode": "none",
      "reflection_count": 1
    },
    {
      "qid": "hp132",
      "agent_type": "reflexion",
      "gold_answer": "Pacific Ocean",
      "predicted_answer": "Pacific Ocean",
      "is_correct": true,
      "attempts": 1,
      "failure_mode": "none",
      "reflection_count": 0
    },
    {
      "qid": "hp133",
      "agent_type": "reflexion",
      "gold_answer": "Paris",
      "predicted_answer": "Paris",
      "is_correct": true,
      "attempts": 1,
      "failure_mode": "none",
      "reflection_count": 0
    },
    {
      "qid": "hp134",
      "agent_type": "reflexion",
      "gold_answer": "violin",
      "predicted_answer": "violin",
      "is_correct": true,
      "attempts": 1,
      "failure_mode": "none",
      "reflection_count": 0
    },
    {
      "qid": "hp135",
      "agent_type": "reflexion",
      "gold_answer": "Oxford University",
      "predicted_answer": "Oxford University",
      "is_correct": true,
      "attempts": 1,
      "failure_mode": "none",
      "reflection_count": 0
    },
    {
      "qid": "hp136",
      "agent_type": "reflexion",
      "gold_answer": "River Thames",
      "predicted_answer": "Thames",
      "is_correct": false,
      "attempts": 3,
      "failure_mode": "wrong_final_answer",
      "reflection_count": 2
    },
    {
      "qid": "hp137",
      "agent_type": "reflexion",
      "gold_answer": "Pacific Ocean",
      "predicted_answer": "Pacific Ocean",
      "is_correct": true,
      "attempts": 1,
      "failure_mode": "none",
      "reflection_count": 0
    },
    {
      "qid": "hp138",
      "agent_type": "reflexion",
      "gold_answer": "Paris",
      "predicted_answer": "Paris",
      "is_correct": true,
      "attempts": 1,
      "failure_mode": "none",
      "reflection_count": 0
    },
    {
      "qid": "hp139",
      "agent_type": "reflexion",
      "gold_answer": "violin",
      "predicted_answer": "violin",
      "is_correct": true,
      "attempts": 1,
      "failure_mode": "none",
      "reflection_count": 0
    },
    {
      "qid": "hp140",
      "agent_type": "reflexion",
      "gold_answer": "Oxford University",
      "predicted_answer": "Oxford University",
      "is_correct": true,
      "attempts": 1,
      "failure_mode": "none",
      "reflection_count": 0
    },
    {
      "qid": "hp141",
      "agent_type": "reflexion",
      "gold_answer": "River Thames",
      "predicted_answer": "River Thames",
      "is_correct": true,
      "attempts": 2,
      "failure_mode": "none",
      "reflection_count": 1
    },
    {
      "qid": "hp142",
      "agent_type": "reflexion",
      "gold_answer": "Pacific Ocean",
      "predicted_answer": "Pacific Ocean",
      "is_correct": true,
      "attempts": 1,
      "failure_mode": "none",
      "reflection_count": 0
    },
    {
      "qid": "hp143",
      "agent_type": "reflexion",
      "gold_answer": "Paris",
      "predicted_answer": "Paris",
      "is_correct": true,
      "attempts": 1,
      "failure_mode": "none",
      "reflection_count": 0
    },
    {
      "qid": "hp144",
      "agent_type": "reflexion",
      "gold_answer": "violin",
      "predicted_answer": "violin",
      "is_correct": true,
      "attempts": 1,
      "failure_mode": "none",
      "reflection_count": 0
    },
    {
      "qid": "hp145",
      "agent_type": "reflexion",
      "gold_answer": "Oxford University",
      "predicted_answer": "Oxford University",
      "is_correct": true,
      "attempts": 1,
      "failure_mode": "none",
      "reflection_count": 0
    },
    {
      "qid": "hp146",
      "agent_type": "reflexion",
      "gold_answer": "River Thames",
      "predicted_answer": "River Thames",
      "is_correct": true,
      "attempts": 3,
      "failure_mode": "none",
      "reflection_count": 2
    },
    {
      "qid": "hp147",
      "agent_type": "reflexion",
      "gold_answer": "Pacific Ocean",
      "predicted_answer": "Pacific Ocean",
      "is_correct": true,
      "attempts": 1,
      "failure_mode": "none",
      "reflection_count": 0
    },
    {
      "qid": "hp148",
      "agent_type": "reflexion",
      "gold_answer": "Paris",
      "predicted_answer": "Paris",
      "is_correct": true,
      "attempts": 1,
      "failure_mode": "none",
      "reflection_count": 0
    },
    {
      "qid": "hp149",
      "agent_type": "reflexion",
      "gold_answer": "violin",
      "predicted_answer": "violin",
      "is_correct": true,
      "attempts": 1,
      "failure_mode": "none",
      "reflection_count": 0
    },
    {
      "qid": "hp150",
      "agent_type": "reflexion",
      "gold_answer": "Oxford University",
      "predicted_answer": "Oxford University",
      "is_correct": true,
      "attempts": 1,
      "failure_mode": "none",
      "reflection_count": 0
    },
    {
      "qid": "hp151",
      "agent_type": "reflexion",
      "gold_answer": "River Thames",
      "predicted_answer": "River Thames",
      "is_correct": true,
      "attempts": 3,
      "failure_mode": "none",
      "reflection_count": 2
    },
    {
      "qid": "hp152",
      "agent_type": "reflexion",
      "gold_answer": "Pacific Ocean",
      "predicted_answer": "Pacific Ocean",
      "is_correct": true,
      "attempts": 1,
      "failure_mode": "none",
      "reflection_count": 0
    },
    {
      "qid": "hp153",
      "agent_type": "reflexion",
      "gold_answer": "Paris",
      "predicted_answer": "Paris",
      "is_correct": true,
      "attempts": 1,
      "failure_mode": "none",
      "reflection_count": 0
    },
    {
      "qid": "hp154",
      "agent_type": "reflexion",
      "gold_answer": "violin",
      "predicted_answer": "violin",
      "is_correct": true,
      "attempts": 1,
      "failure_mode": "none",
      "reflection_count": 0
    },
    {
      "qid": "hp155",
      "agent_type": "reflexion",
      "gold_answer": "Oxford University",
      "predicted_answer": "Oxford University",
      "is_correct": true,
      "attempts": 1,
      "failure_mode": "none",
      "reflection_count": 0
    },
    {
      "qid": "hp156",
      "agent_type": "reflexion",
      "gold_answer": "River Thames",
      "predicted_answer": "River Thames",
      "is_correct": true,
      "attempts": 2,
      "failure_mode": "none",
      "reflection_count": 1
    },
    {
      "qid": "hp157",
      "agent_type": "reflexion",
      "gold_answer": "Pacific Ocean",
      "predicted_answer": "Pacific Ocean",
      "is_correct": true,
      "attempts": 1,
      "failure_mode": "none",
      "reflection_count": 0
    },
    {
      "qid": "hp158",
      "agent_type": "reflexion",
      "gold_answer": "Paris",
      "predicted_answer": "Paris",
      "is_correct": true,
      "attempts": 1,
      "failure_mode": "none",
      "reflection_count": 0
    },
    {
      "qid": "hp159",
      "agent_type": "reflexion",
      "gold_answer": "violin",
      "predicted_answer": "violin",
      "is_correct": true,
      "attempts": 1,
      "failure_mode": "none",
      "reflection_count": 0
    },
    {
      "qid": "hp160",
      "agent_type": "reflexion",
      "gold_answer": "Oxford University",
      "predicted_answer": "Oxford University",
      "is_correct": true,
      "attempts": 1,
      "failure_mode": "none",
      "reflection_count": 0
    },
    {
      "qid": "hp161",
      "agent_type": "reflexion",
      "gold_answer": "River Thames",
      "predicted_answer": "River Thames",
      "is_correct": true,
      "attempts": 3,
      "failure_mode": "none",
      "reflection_count": 2
    },
    {
      "qid": "hp162",
      "agent_type": "reflexion",
      "gold_answer": "Pacific Ocean",
      "predicted_answer": "Pacific Ocean",
      "is_correct": true,
      "attempts": 1,
      "failure_mode": "none",
      "reflection_count": 0
    },
    {
      "qid": "hp163",
      "agent_type": "reflexion",
      "gold_answer": "Paris",
      "predicted_answer": "Paris",
      "is_correct": true,
      "attempts": 1,
      "failure_mode": "none",
      "reflection_count": 0
    },
    {
      "qid": "hp164",
      "agent_type": "reflexion",
      "gold_answer": "violin",
      "predicted_answer": "violin",
      "is_correct": true,
      "attempts": 1,
      "failure_mode": "none",
      "reflection_count": 0
    },
    {
      "qid": "hp165",
      "agent_type": "reflexion",
      "gold_answer": "Oxford University",
      "predicted_answer": "Oxford University",
      "is_correct": true,
      "attempts": 1,
      "failure_mode": "none",
      "reflection_count": 0
    },
    {
      "qid": "hp166",
      "agent_type": "reflexion",
      "gold_answer": "River Thames",
      "predicted_answer": "Thames",
      "is_correct": false,
      "attempts": 3,
      "failure_mode": "wrong_final_answer",
      "reflection_count": 2
    },
    {
      "qid": "hp167",
      "agent_type": "reflexion",
      "gold_answer": "Pacific Ocean",
      "predicted_answer": "Pacific Ocean",
      "is_correct": true,
      "attempts": 1,
      "failure_mode": "none",
      "reflection_count": 0
    },
    {
      "qid": "hp168",
      "agent_type": "reflexion",
      "gold_answer": "Paris",
      "predicted_answer": "Paris",
      "is_correct": true,
      "attempts": 1,
      "failure_mode": "none",
      "reflection_count": 0
    },
    {
      "qid": "hp169",
      "agent_type": "reflexion",
      "gold_answer": "violin",
      "predicted_answer": "violin",
      "is_correct": true,
      "attempts": 1,
      "failure_mode": "none",
      "reflection_count": 0
    },
    {
      "qid": "hp170",
      "agent_type": "reflexion",
      "gold_answer": "Oxford University",
      "predicted_answer": "Oxford University",
      "is_correct": true,
      "attempts": 1,
      "failure_mode": "none",
      "reflection_count": 0
    },
    {
      "qid": "hp171",
      "agent_type": "reflexion",
      "gold_answer": "River Thames",
      "predicted_answer": "River Thames",
      "is_correct": true,
      "attempts": 2,
      "failure_mode": "none",
      "reflection_count": 1
    },
    {
      "qid": "hp172",
      "agent_type": "reflexion",
      "gold_answer": "Pacific Ocean",
      "predicted_answer": "Pacific Ocean",
      "is_correct": true,
      "attempts": 1,
      "failure_mode": "none",
      "reflection_count": 0
    },
    {
      "qid": "hp173",
      "agent_type": "reflexion",
      "gold_answer": "Paris",
      "predicted_answer": "Paris",
      "is_correct": true,
      "attempts": 1,
      "failure_mode": "none",
      "reflection_count": 0
    },
    {
      "qid": "hp174",
      "agent_type": "reflexion",
      "gold_answer": "violin",
      "predicted_answer": "violin",
      "is_correct": true,
      "attempts": 1,
      "failure_mode": "none",
      "reflection_count": 0
    },
    {
      "qid": "hp175",
      "agent_type": "reflexion",
      "gold_answer": "Oxford University",
      "predicted_answer": "Oxford University",
      "is_correct": true,
      "attempts": 1,
      "failure_mode": "none",
      "reflection_count": 0
    },
    {
      "qid": "hp176",
      "agent_type": "reflexion",
      "gold_answer": "River Thames",
      "predicted_answer": "Thames",
      "is_correct": false,
      "attempts": 3,
      "failure_mode": "wrong_final_answer",
      "reflection_count": 2
    },
    {
      "qid": "hp177",
      "agent_type": "reflexion",
      "gold_answer": "Pacific Ocean",
      "predicted_answer": "Pacific Ocean",
      "is_correct": true,
      "attempts": 1,
      "failure_mode": "none",
      "reflection_count": 0
    },
    {
      "qid": "hp178",
      "agent_type": "reflexion",
      "gold_answer": "Paris",
      "predicted_answer": "Paris",
      "is_correct": true,
      "attempts": 1,
      "failure_mode": "none",
      "reflection_count": 0
    },
    {
      "qid": "hp179",
      "agent_type": "reflexion",
      "gold_answer": "violin",
      "predicted_answer": "violin",
      "is_correct": true,
      "attempts": 1,
      "failure_mode": "none",
      "reflection_count": 0
    },
    {
      "qid": "hp180",
      "agent_type": "reflexion",
      "gold_answer": "Oxford University",
      "predicted_answer": "Oxford University",
      "is_correct": true,
      "attempts": 1,
      "failure_mode": "none",
      "reflection_count": 0
    },
    {
      "qid": "hp181",
      "agent_type": "reflexion",
      "gold_answer": "River Thames",
      "predicted_answer": "Thames",
      "is_correct": false,
      "attempts": 3,
      "failure_mode": "wrong_final_answer",
      "reflection_count": 2
    },
    {
      "qid": "hp182",
      "agent_type": "reflexion",
      "gold_answer": "Pacific Ocean",
      "predicted_answer": "Pacific Ocean",
      "is_correct": true,
      "attempts": 1,
      "failure_mode": "none",
      "reflection_count": 0
    },
    {
      "qid": "hp183",
      "agent_type": "reflexion",
      "gold_answer": "Paris",
      "predicted_answer": "Paris",
      "is_correct": true,
      "attempts": 1,
      "failure_mode": "none",
      "reflection_count": 0
    },
    {
      "qid": "hp184",
      "agent_type": "reflexion",
      "gold_answer": "violin",
      "predicted_answer": "violin",
      "is_correct": true,
      "attempts": 1,
      "failure_mode": "none",
      "reflection_count": 0
    },
    {
      "qid": "hp185",
      "agent_type": "reflexion",
      "gold_answer": "Oxford University",
      "predicted_answer": "Oxford University",
      "is_correct": true,
      "attempts": 1,
      "failure_mode": "none",
      "reflection_count": 0
    },
    {
      "qid": "hp186",
      "agent_type": "reflexion",
      "gold_answer": "River Thames",
      "predicted_answer": "River Thames",
      "is_correct": true,
      "attempts": 2,
      "failure_mode": "none",
      "reflection_count": 1
    },
    {
      "qid": "hp187",
      "agent_type": "reflexion",
      "gold_answer": "Pacific Ocean",
      "predicted_answer": "Pacific Ocean",
      "is_correct": true,
      "attempts": 1,
      "failure_mode": "none",
      "reflection_count": 0
    },
    {
      "qid": "hp188",
      "agent_type": "reflexion",
      "gold_answer": "Paris",
      "predicted_answer": "Paris",
      "is_correct": true,
      "attempts": 1,
      "failure_mode": "none",
      "reflection_count": 0
    },
    {
      "qid": "hp189",
      "agent_type": "reflexion",
      "gold_answer": "violin",
      "predicted_answer": "violin",
      "is_correct": true,
      "attempts": 1,
      "failure_mode": "none",
      "reflection_count": 0
    },
    {
      "qid": "hp190",
      "agent_type": "reflexion",
      "gold_answer": "Oxford University",
      "predicted_answer": "Oxford University",
      "is_correct": true,
      "attempts": 1,
      "failure_mode": "none",
      "reflection_count": 0
    },
    {
      "qid": "hp191",
      "agent_type": "reflexion",
      "gold_answer": "River Thames",
      "predicted_answer": "River Thames",
      "is_correct": true,
      "attempts": 3,
      "failure_mode": "none",
      "reflection_count": 2
    },
    {
      "qid": "hp192",
      "agent_type": "reflexion",
      "gold_answer": "Pacific Ocean",
      "predicted_answer": "Pacific Ocean",
      "is_correct": true,
      "attempts": 1,
      "failure_mode": "none",
      "reflection_count": 0
    },
    {
      "qid": "hp193",
      "agent_type": "reflexion",
      "gold_answer": "Paris",
      "predicted_answer": "Paris",
      "is_correct": true,
      "attempts": 1,
      "failure_mode": "none",
      "reflection_count": 0
    },
    {
      "qid": "hp194",
      "agent_type": "reflexion",
      "gold_answer": "violin",
      "predicted_answer": "violin",
      "is_correct": true,
      "attempts": 1,
      "failure_mode": "none",
      "reflection_count": 0
    },
    {
      "qid": "hp195",
      "agent_type": "reflexion",
      "gold_answer": "Oxford University",
      "predicted_answer": "Oxford",
      "is_correct": true,
      "attempts": 1,
      "failure_mode": "none",
      "reflection_count": 0
    },
    {
      "qid": "hp196",
      "agent_type": "reflexion",
      "gold_answer": "River Thames",
      "predicted_answer": "River Thames",
      "is_correct": true,
      "attempts": 2,
      "failure_mode": "none",
      "reflection_count": 1
    },
    {
      "qid": "hp197",
      "agent_type": "reflexion",
      "gold_answer": "Pacific Ocean",
      "predicted_answer": "Pacific Ocean",
      "is_correct": true,
      "attempts": 1,
      "failure_mode": "none",
      "reflection_count": 0
    },
    {
      "qid": "hp198",
      "agent_type": "reflexion",
      "gold_answer": "Paris",
      "predicted_answer": "Paris",
      "is_correct": true,
      "attempts": 1,
      "failure_mode": "none",
      "reflection_count": 0
    },
    {
      "qid": "hp199",
      "agent_type": "reflexion",
      "gold_answer": "violin",
      "predicted_answer": "violin",
      "is_correct": true,
      "attempts": 1,
      "failure_mode": "none",
      "reflection_count": 0
    }
  ],
  "extensions": [
    "structured_evaluator",
    "reflection_memory",
    "benchmark_report_json",
    "adaptive_max_attempts",
    "plan_then_execute"
  ],
  "discussion": "Reflexion Agent significantly outperforms the basic ReAct agent on multi-hop questions because it can learn from failed attempts. When the first attempt fails due to incomplete reasoning (e.g., stopping after the first hop), the Reflector analyzes the failure and provides targeted guidance for the next attempt. This is particularly effective for questions requiring multiple hops of reasoning, such as \"What river flows through the city where Ada Lovelace was born?\"\n\nThe key improvements from Reflexion include:\n1. The agent doesn't repeat the same mistake on subsequent attempts\n2. The reflection memory provides context-aware guidance based on actual failures\n3. The structured evaluator ensures consistent scoring with detailed feedback\n\nFailure modes that remain challenging include entity_drift (answering a related but wrong entity) and incomplete_multi_hop (stopping early without completing all reasoning steps). These would require more sophisticated prompt engineering or additional context to fully resolve.\n\nToken usage is higher for Reflexion due to the extra LLM calls for evaluation and reflection, but this cost is justified by improved accuracy on complex multi-hop questions. The tradeoff between cost and accuracy should be considered when deploying in production systems."
}